[
  {
    "ContainingType": "LinkAPI.Controllers.ContactsController",
    "Method": "AddNewContact",
    "RelativePath": "api/Contacts/AddNewContact/{u_id}/{Contact_id}",
    "HttpMethod": "POST",
    "IsController": true,
    "Order": 0,
    "Parameters": [
      {
        "Name": "u_id",
        "Type": "System.Decimal",
        "IsRequired": true
      },
      {
        "Name": "Contact_id",
        "Type": "System.Decimal",
        "IsRequired": true
      }
    ],
    "ReturnTypes": []
  },
  {
    "ContainingType": "LinkAPI.Controllers.ContactsController",
    "Method": "DeleteContact",
    "RelativePath": "api/Contacts/DeleteContact/{u_id}/{Contact_id}",
    "HttpMethod": "DELETE",
    "IsController": true,
    "Order": 0,
    "Parameters": [
      {
        "Name": "u_id",
        "Type": "System.Decimal",
        "IsRequired": true
      },
      {
        "Name": "Contact_id",
        "Type": "System.Decimal",
        "IsRequired": true
      }
    ],
    "ReturnTypes": []
  },
  {
    "ContainingType": "LinkAPI.Controllers.ContactsController",
    "Method": "GetAllContacts",
    "RelativePath": "api/Contacts/GetAllContacts/{u_id}",
    "HttpMethod": "GET",
    "IsController": true,
    "Order": 0,
    "Parameters": [
      {
        "Name": "u_id",
        "Type": "System.Decimal",
        "IsRequired": true
      }
    ],
    "ReturnTypes": []
  },
  {
    "ContainingType": "LinkAPI.Controllers.HomeScreenController",
    "Method": "GetActiveUsers",
    "RelativePath": "api/HomeScreen/GetActiveUsers/{userID}",
    "HttpMethod": "GET",
    "IsController": true,
    "Order": 0,
    "Parameters": [
      {
        "Name": "userID",
        "Type": "System.Decimal",
        "IsRequired": true
      }
    ],
    "ReturnTypes": []
  },
  {
    "ContainingType": "LinkAPI.Controllers.HomeScreenController",
    "Method": "GetAllChatsByuserID",
    "RelativePath": "api/HomeScreen/GetAllChatsByuserID/{userID}",
    "HttpMethod": "GET",
    "IsController": true,
    "Order": 0,
    "Parameters": [
      {
        "Name": "userID",
        "Type": "System.Decimal",
        "IsRequired": true
      }
    ],
    "ReturnTypes": []
  },
  {
    "ContainingType": "LinkAPI.Controllers.HomeScreenController",
    "Method": "GetAllUnreadMessagesCount",
    "RelativePath": "api/HomeScreen/GetAllUnreadMessagesCount/{userID}",
    "HttpMethod": "GET",
    "IsController": true,
    "Order": 0,
    "Parameters": [
      {
        "Name": "userID",
        "Type": "System.Decimal",
        "IsRequired": true
      }
    ],
    "ReturnTypes": []
  },
  {
    "ContainingType": "LinkAPI.Controllers.HomeScreenController",
    "Method": "searchForUser",
    "RelativePath": "api/HomeScreen/searchForUser/{userName}",
    "HttpMethod": "GET",
    "IsController": true,
    "Order": 0,
    "Parameters": [
      {
        "Name": "userName",
        "Type": "System.String",
        "IsRequired": true
      }
    ],
    "ReturnTypes": []
  },
  {
    "ContainingType": "LinkAPI.Controllers.ProfileController",
    "Method": "CreateUserProfile",
    "RelativePath": "api/Profile/CreateUserProfile",
    "HttpMethod": "POST",
    "IsController": true,
    "Order": 0,
    "Parameters": [
      {
        "Name": "profile",
        "Type": "Link.Core.DTO.linkUserDto",
        "IsRequired": true
      }
    ],
    "ReturnTypes": []
  },
  {
    "ContainingType": "LinkAPI.Controllers.ProfileController",
    "Method": "GetUserProfile",
    "RelativePath": "api/Profile/GetUserProfile/user_id",
    "HttpMethod": "GET",
    "IsController": true,
    "Order": 0,
    "Parameters": [
      {
        "Name": "user_id",
        "Type": "System.Decimal",
        "IsRequired": false
      }
    ],
    "ReturnTypes": []
  },
  {
    "ContainingType": "LinkAPI.Controllers.ProfileController",
    "Method": "UpdateUserProfile",
    "RelativePath": "api/Profile/UpdateUserProfile",
    "HttpMethod": "PUT",
    "IsController": true,
    "Order": 0,
    "Parameters": [
      {
        "Name": "profile",
        "Type": "Link.Core.DTO.linkUserDto",
        "IsRequired": true
      }
    ],
    "ReturnTypes": []
  }
]